notify_sms_py/__init__.py
notify_sms_py/notify_sms.py
notify_sms_py/notify_types.py
notify_sms_py-1.1.2.dist-info/METADATA
notify_sms_py-1.1.2.dist-info/WHEEL
notify_sms_py-1.1.2.dist-info/licenses/LICENSE
notify_sms_py-1.1.2.dist-info/RECORD
