Metadata-Version: 2.3
Name: notify_sms_py
Version: 1.1.2
Summary: Notify is a bulk SMS Module for sending SMS's accross local zambian phone numbers. It is embedded in [GameBox - Download the app here.]( https://play.google.com/store/apps/details?id=com.microtech.gamebox)
Project-URL: homepage, https://github.com/patrickkabwe/notify_sms
Project-URL: issues, https://github.com/patrickkabwe/notify_sms/issues
Author-email: Patrick Kabwe <patrickckabwe@gmail.com>
License-File: LICENSE
Keywords: bulk sms,sms,zambia
Classifier: Development Status :: 5 - Production/Stable
Classifier: Intended Audience :: Developers
Classifier: License :: OSI Approved :: MIT License
Classifier: Operating System :: OS Independent
Classifier: Programming Language :: Python :: 3.8
Classifier: Programming Language :: Python :: 3.9
Classifier: Programming Language :: Python :: 3.10
Requires-Python: >=3.12
Requires-Dist: importlib-metadata; python_version < '3.10'
Requires-Dist: requests
